eidolon_ai_usage_client/__init__.py
eidolon_ai_usage_client/client.py
eidolon_ai_usage_client/models.py
eidolon_ai_usage_client-0.1.10.dist-info/METADATA
eidolon_ai_usage_client-0.1.10.dist-info/WHEEL
eidolon_ai_usage_client-0.1.10.dist-info/RECORD
